pylars/__init__.py
pylars/pylar.py
pylars/steps.py
pylars/utils.py
pylars/dsl/__init__.py
pylars/dsl/aggs.py
pylars/dsl/base.py
pylars/dsl/exprdsl.py
pylars/dsl/stringdsl.py
pylars/expr/__init__.py
pylars/expr/agg_expr.py
pylars/expr/alias.py
pylars/expr/astype.py
pylars/expr/binary_expr.py
pylars/expr/column.py
pylars/expr/desc.py
pylars/expr/expr.py
pylars/expr/litteral.py
pylars/expr/result.py
pylars/expr/stringops.py
pylars/expr/unary_expr.py
pylars-0.1.3.dist-info/METADATA
pylars-0.1.3.dist-info/WHEEL
pylars-0.1.3.dist-info/top_level.txt
pylars-0.1.3.dist-info/RECORD
